raven_aiohttp.py
raven_aiohttp_redux-0.1.0.dist-info/LICENSE
raven_aiohttp_redux-0.1.0.dist-info/METADATA
raven_aiohttp_redux-0.1.0.dist-info/WHEEL
raven_aiohttp_redux-0.1.0.dist-info/top_level.txt
raven_aiohttp_redux-0.1.0.dist-info/RECORD
